drt_sdk_core/__init__.py
drt_sdk_core/account.py
drt_sdk_core/account_test.py
drt_sdk_core/address.py
drt_sdk_core/address_test.py
drt_sdk_core/bech32.py
drt_sdk_core/code_metadata.py
drt_sdk_core/code_metadata_test.py
drt_sdk_core/codec.py
drt_sdk_core/codec_test.py
drt_sdk_core/constants.py
drt_sdk_core/contract_query.py
drt_sdk_core/contract_query_builder.py
drt_sdk_core/contract_query_builder_test.py
drt_sdk_core/errors.py
drt_sdk_core/interfaces.py
drt_sdk_core/message.py
drt_sdk_core/message_test.py
drt_sdk_core/serializer.py
drt_sdk_core/token_payment.py
drt_sdk_core/token_payment_test.py
drt_sdk_core/tokens.py
drt_sdk_core/tokens_test.py
drt_sdk_core/transaction.py
drt_sdk_core/transaction_payload.py
drt_sdk_core/transaction_test.py
drt_sdk_core/typecheck.py
drt_sdk_core/proto/__init__.py
drt_sdk_core/proto/transaction.proto
drt_sdk_core/proto/transaction_pb2.py
drt_sdk_core/proto/transaction_pb2.pyi
drt_sdk_core/proto/transaction_serializer.py
drt_sdk_core/proto/transaction_serializer_test.py
drt_sdk_core/testutils/wallets.py
drt_sdk_core/testutils/testdata/adder.wasm
drt_sdk_core/testutils/testwallets/alice.pem
drt_sdk_core/testutils/testwallets/bob.pem
drt_sdk_core/testutils/testwallets/carol.pem
drt_sdk_core/testutils/testwallets/frank.pem
drt_sdk_core/testutils/testwallets/grace.pem
drt_sdk_core/transaction_builders/__init__.py
drt_sdk_core/transaction_builders/contract_builders.py
drt_sdk_core/transaction_builders/contract_builders_test.py
drt_sdk_core/transaction_builders/dcdt_builders.py
drt_sdk_core/transaction_builders/dcdt_builders_test.py
drt_sdk_core/transaction_builders/default_configuration.py
drt_sdk_core/transaction_builders/default_configuration_test.py
drt_sdk_core/transaction_builders/other_builders.py
drt_sdk_core/transaction_builders/relayed_v1_builder.py
drt_sdk_core/transaction_builders/relayed_v1_builder_test.py
drt_sdk_core/transaction_builders/relayed_v2_builder.py
drt_sdk_core/transaction_builders/relayed_v2_builder_test.py
drt_sdk_core-0.0.3.dist-info/METADATA
drt_sdk_core-0.0.3.dist-info/WHEEL
drt_sdk_core-0.0.3.dist-info/licenses/LICENSE
drt_sdk_core-0.0.3.dist-info/RECORD
