Metadata-Version: 2.3
Name: drt-sdk-core
Version: 0.0.3
Summary: Core components of the Dharitri Python SDK.
Project-URL: Homepage, https://github.com/DharitriOne/drt-sdk-py-core
Author: Dharitri
License-Expression: MIT
License-File: LICENSE
Classifier: License :: OSI Approved :: MIT License
Classifier: Operating System :: OS Independent
Classifier: Programming Language :: Python :: 3
Requires-Python: >=3.8
Requires-Dist: protobuf==3.20.2
Requires-Dist: pycryptodomex==3.19.1
